f1tel_gui/F1tel.py
f1tel_gui/__init__.py
f1tel_gui/__main__.py
f1tel_gui/graph_layout.json
f1tel_gui/utils.py
f1tel_gui/design/loading_dialog.ui
f1tel_gui/design/main.ui
f1tel_gui/img/logo.jpg
f1tel_gui/thread/load_f1_obj.py
f1tel_gui/windows/MplCanvas.py
f1tel_gui/windows/loading_dialog.py
f1tel_gui/windows/main.py
f1tel_gui/windows/jsoneditor/JSONitor.py
f1tel_gui/windows/jsoneditor/JSONitor.ui
f1tel_gui/windows/jsoneditor/JSONitorHistory.json
f1tel_gui/windows/jsoneditor/JSONitorSettings.json
f1tel_gui/windows/jsoneditor/JSONitorUI.py
f1tel_gui/windows/jsoneditor/Utilities/JSONTools.py
f1tel_gui/windows/jsoneditor/Utilities/__init__.py
f1tel_gui-1.0.3.dist-info/LICENSE
f1tel_gui-1.0.3.dist-info/METADATA
f1tel_gui-1.0.3.dist-info/WHEEL
f1tel_gui-1.0.3.dist-info/entry_points.txt
f1tel_gui-1.0.3.dist-info/top_level.txt
f1tel_gui-1.0.3.dist-info/RECORD
