Metadata-Version: 2.1
Name: f1tel-gui
Version: 1.0.3
Summary: F1 Telemetry Display
Home-page: UNKNOWN
Author: Barbato Federico
Author-email: barbato.federico01@outlook.com
License: UNKNOWN
Keywords: python,formula 1,telemetry,display,f1
Platform: UNKNOWN
Classifier: Development Status :: 5 - Production/Stable
Classifier: Intended Audience :: Education
Classifier: Programming Language :: Python :: 3
Classifier: Operating System :: MacOS :: MacOS X
Classifier: Operating System :: Microsoft :: Windows
License-File: LICENSE
Requires-Dist: PyQt5
Requires-Dist: Qscintilla
Requires-Dist: QtAwesome
Requires-Dist: fastf1
Requires-Dist: jsonschema
Requires-Dist: matplotlib
Requires-Dist: numpy
Requires-Dist: pandas
Requires-Dist: pyperclip
Requires-Dist: pyqt5
Requires-Dist: qdarkstyle
